tests/__init__.py
tests/test_article.py
web_article/__init__.py
web_article/article.py
web_article/bin.py
web_article/selectors.py
web_article/version.json
web_article-1.0.0.dist-info/LICENSE
web_article-1.0.0.dist-info/METADATA
web_article-1.0.0.dist-info/WHEEL
web_article-1.0.0.dist-info/entry_points.txt
web_article-1.0.0.dist-info/top_level.txt
web_article-1.0.0.dist-info/RECORD
