Metadata-Version: 2.1
Name: web-article
Version: 1.0.0
Summary: get title and text for given web url
Home-page: https://github.com/suqingdong/web_article
Author: suqingdong
Author-email: suqingdong1114@gmail.com
License: MIT License
Platform: UNKNOWN
Classifier: Development Status :: 5 - Production/Stable
Classifier: Operating System :: OS Independent
Classifier: Intended Audience :: Developers
Classifier: License :: OSI Approved :: MIT License
Classifier: Programming Language :: Python
Classifier: Programming Language :: Python :: 3
Classifier: Programming Language :: Python :: 3.8
Classifier: Programming Language :: Python :: 3.9
Classifier: Topic :: Software Development :: Libraries
Requires-Dist: click
Requires-Dist: simple-loggers (>=1.0.5)
Requires-Dist: webrequests (>=1.0.8)
